LICENSE.md
MANIFEST.in
README.md
setup.py
bin/konstrukteur
bin/konstrukteur.bat
konstrukteur/FileManager.py
konstrukteur/FileWatcher.py
konstrukteur/HtmlParser.py
konstrukteur/Konstrukteur.py
konstrukteur/Language.py
konstrukteur/__init__.py
konstrukteur.egg-info/PKG-INFO
konstrukteur.egg-info/SOURCES.txt
konstrukteur.egg-info/dependency_links.txt
konstrukteur.egg-info/requires.txt
konstrukteur.egg-info/top_level.txt
konstrukteurlibs/watchdog/run_tests.py
konstrukteurlibs/watchdog/setup.py
konstrukteurlibs/watchdog/docs/source/conf.py
konstrukteurlibs/watchdog/docs/source/examples/logger.py
konstrukteurlibs/watchdog/docs/source/examples/patterns.py
konstrukteurlibs/watchdog/docs/source/examples/simple.py
konstrukteurlibs/watchdog/src/watchdog/__init__.py
konstrukteurlibs/watchdog/src/watchdog/events.py
konstrukteurlibs/watchdog/src/watchdog/version.py
konstrukteurlibs/watchdog/src/watchdog/watchmedo.py
konstrukteurlibs/watchdog/src/watchdog/observers/__init__.py
konstrukteurlibs/watchdog/src/watchdog/observers/api.py
konstrukteurlibs/watchdog/src/watchdog/observers/fsevents.py
konstrukteurlibs/watchdog/src/watchdog/observers/inotify.py
konstrukteurlibs/watchdog/src/watchdog/observers/inotify_c.py
konstrukteurlibs/watchdog/src/watchdog/observers/kqueue.py
konstrukteurlibs/watchdog/src/watchdog/observers/polling.py
konstrukteurlibs/watchdog/src/watchdog/observers/read_directory_changes.py
konstrukteurlibs/watchdog/src/watchdog/observers/read_directory_changes_async.py
konstrukteurlibs/watchdog/src/watchdog/observers/winapi.py
konstrukteurlibs/watchdog/src/watchdog/observers/winapi_common.py
konstrukteurlibs/watchdog/src/watchdog/tricks/__init__.py
konstrukteurlibs/watchdog/src/watchdog/utils/__init__.py
konstrukteurlibs/watchdog/src/watchdog/utils/bricks.py
konstrukteurlibs/watchdog/src/watchdog/utils/decorators.py
konstrukteurlibs/watchdog/src/watchdog/utils/dirsnapshot.py
konstrukteurlibs/watchdog/src/watchdog/utils/echo.py
konstrukteurlibs/watchdog/src/watchdog/utils/importlib2.py
konstrukteurlibs/watchdog/src/watchdog/utils/platform.py
konstrukteurlibs/watchdog/src/watchdog/utils/unicode_paths.py
