Metadata-Version: 1.1
Name: konstrukteur
Version: 0.1.7
Summary: Static website generator
Home-page: http://github.com/fastner/konstrukteur
Author: Sebastian Software
Author-email: team@sebastian-software.de
License: MIT
Download-URL: http://pypi.python.org/packages/source/k/konstrukteur/konstrukteur-0.1.7.zip
Platform: any
Classifier: Development Status :: 4 - Beta
Classifier: Environment :: Console
Classifier: Intended Audience :: Developers
Classifier: License :: OSI Approved :: MIT License
Classifier: License :: Freely Distributable
Classifier: Operating System :: OS Independent
Classifier: Programming Language :: Python
Classifier: Programming Language :: Python :: 3
Classifier: Programming Language :: Python :: 3.2
Classifier: Programming Language :: Python :: 3.3
Classifier: Topic :: Software Development :: Code Generators
Classifier: Topic :: Software Development :: Internationalization
Classifier: Topic :: Internet :: WWW/HTTP
